pyhaloxmlc.cpython-313-darwin.so
pyhaloxml-3.1.2.dist-info/RECORD
pyhaloxml-3.1.2.dist-info/WHEEL
pyhaloxml-3.1.2.dist-info/METADATA
pyhaloxml/misc.py
pyhaloxml/version.py
pyhaloxml/Region.py
pyhaloxml/__init__.py
pyhaloxml/HaloXML.py
pyhaloxml/Layer.py
pyhaloxml/py.typed
pyhaloxml/ellipse.py
pyhaloxml/shapely/__init__.py
pyhaloxml/shapely/to_shapely.py
