Metadata-Version: 2.1
Name: pyhaloxml
Version: 3.1.2
Summary: Read and write the annotation files from Halo
Keywords: Halo,reader,annotation
Author-Email: Rolf Harkes <r.harkes@nki.nl>
Classifier: License :: OSI Approved :: GNU General Public License v3 or later (GPLv3+)
Classifier: Programming Language :: Python
Classifier: Programming Language :: Python :: 3
Project-URL: Homepage, https://github.com/rharkes/pyhaloxml
Requires-Python: >=3.10
Requires-Dist: lxml>=4.9
Requires-Dist: geojson>=3.0
Requires-Dist: python-dateutil
Requires-Dist: shapely>=2.0; extra == "shapely"
Requires-Dist: black; extra == "dev"
Requires-Dist: bumpver; extra == "dev"
Requires-Dist: pytest; extra == "dev"
Requires-Dist: mypy; extra == "dev"
Requires-Dist: types-python-dateutil; extra == "dev"
Requires-Dist: lxml-stubs; extra == "dev"
Provides-Extra: shapely
Provides-Extra: dev
